setup.cfg
setup.py
src/__init__.py
src/alert.py
src/client.py
src/connection.py
src/file.py
src/instanttest.py
src/load.py
src/maintenance.py
src/monitor.py
src/rum.py
src/script.py
wpm_api_client.egg-info/PKG-INFO
wpm_api_client.egg-info/SOURCES.txt
wpm_api_client.egg-info/dependency_links.txt
wpm_api_client.egg-info/not-zip-safe
wpm_api_client.egg-info/requires.txt
wpm_api_client.egg-info/top_level.txt