Metadata-Version: 1.1
Name: wpm-api-client
Version: 2.7.1
Summary: A Python library for the Web Performance Management API
Home-page: https://github.com/neustar/wpm_api_client
Author: Shane Barbetta
Author-email: shane@barbetta.me
License: Apache License, Version 2.0
Keywords: wpm_api_client
Platform: UNKNOWN
Classifier: Development Status :: 5 - Production/Stable
Classifier: Topic :: Utilities
Classifier: License :: OSI Approved :: Apache Software License
